<Item>
  <ASIN>4764903350</ASIN>
  <DetailPageURL>http://www.amazon.co.jp/%E3%82%A2%E3%83%AB%E3%82%B4%E3%83%AA%E3%82%BA%E3%83%A0%E3%81%AE%E8%A8%AD%E8%A8%88%E3%81%A8%E8%A7%A3%E6%9E%90%E6%89%8B%E6%B3%95-%E3%82%A2%E3%83%AB%E3%82%B4%E3%83%AA%E3%82%BA%E3%83%A0%E3%82%A4%E3%83%B3%E3%83%88%E3%83%AD%E3%83%80%E3%82%AF%E3%82%B7%E3%83%A7%E3%83%B3-T-%E3%82%B3%E3%83%AB%E3%83%A1%E3%83%B3/dp/4764903350%3FSubscriptionId%3DAKIAJTLVJPAVA2KR4PJA%26tag%3Dnitoyoncom-22%26linkCode%3Dxm2%26camp%3D2025%26creative%3D165953%26creativeASIN%3D4764903350</DetailPageURL>
  <ItemLinks>
    <ItemLink>
      <Description>Add To Wishlist</Description>
      <URL>http://www.amazon.co.jp/gp/registry/wishlist/add-item.html%3Fasin.0%3D4764903350%26SubscriptionId%3DAKIAJTLVJPAVA2KR4PJA%26tag%3Dnitoyoncom-22%26linkCode%3Dxm2%26camp%3D2025%26creative%3D5143%26creativeASIN%3D4764903350</URL>
    </ItemLink>
    <ItemLink>
      <Description>Tell A Friend</Description>
      <URL>http://www.amazon.co.jp/gp/pdp/taf/4764903350%3FSubscriptionId%3DAKIAJTLVJPAVA2KR4PJA%26tag%3Dnitoyoncom-22%26linkCode%3Dxm2%26camp%3D2025%26creative%3D5143%26creativeASIN%3D4764903350</URL>
    </ItemLink>
    <ItemLink>
      <Description>All Customer Reviews</Description>
      <URL>http://www.amazon.co.jp/review/product/4764903350%3FSubscriptionId%3DAKIAJTLVJPAVA2KR4PJA%26tag%3Dnitoyoncom-22%26linkCode%3Dxm2%26camp%3D2025%26creative%3D5143%26creativeASIN%3D4764903350</URL>
    </ItemLink>
    <ItemLink>
      <Description>All Offers</Description>
      <URL>http://www.amazon.co.jp/gp/offer-listing/4764903350%3FSubscriptionId%3DAKIAJTLVJPAVA2KR4PJA%26tag%3Dnitoyoncom-22%26linkCode%3Dxm2%26camp%3D2025%26creative%3D5143%26creativeASIN%3D4764903350</URL>
    </ItemLink>
  </ItemLinks>
  <SmallImage>
    <URL>http://ecx.images-amazon.com/images/I/41ApbsUpEYL._SL75_.jpg</URL>
    <Height Units="pixels">75</Height>
    <Width Units="pixels">53</Width>
  </SmallImage>
  <MediumImage>
    <URL>http://ecx.images-amazon.com/images/I/41ApbsUpEYL._SL160_.jpg</URL>
    <Height Units="pixels">160</Height>
    <Width Units="pixels">113</Width>
  </MediumImage>
  <LargeImage>
    <URL>http://ecx.images-amazon.com/images/I/41ApbsUpEYL.jpg</URL>
    <Height Units="pixels">423</Height>
    <Width Units="pixels">300</Width>
  </LargeImage>
  <ImageSets>
    <ImageSet Category="primary">
      <SwatchImage>
        <URL>http://ecx.images-amazon.com/images/I/41ApbsUpEYL._SL30_.jpg</URL>
        <Height Units="pixels">30</Height>
        <Width Units="pixels">21</Width>
      </SwatchImage>
      <SmallImage>
        <URL>http://ecx.images-amazon.com/images/I/41ApbsUpEYL._SL75_.jpg</URL>
        <Height Units="pixels">75</Height>
        <Width Units="pixels">53</Width>
      </SmallImage>
      <ThumbnailImage>
        <URL>http://ecx.images-amazon.com/images/I/41ApbsUpEYL._SL75_.jpg</URL>
        <Height Units="pixels">75</Height>
        <Width Units="pixels">53</Width>
      </ThumbnailImage>
      <TinyImage>
        <URL>http://ecx.images-amazon.com/images/I/41ApbsUpEYL._SL110_.jpg</URL>
        <Height Units="pixels">110</Height>
        <Width Units="pixels">78</Width>
      </TinyImage>
      <MediumImage>
        <URL>http://ecx.images-amazon.com/images/I/41ApbsUpEYL._SL160_.jpg</URL>
        <Height Units="pixels">160</Height>
        <Width Units="pixels">113</Width>
      </MediumImage>
      <LargeImage>
        <URL>http://ecx.images-amazon.com/images/I/41ApbsUpEYL.jpg</URL>
        <Height Units="pixels">423</Height>
        <Width Units="pixels">300</Width>
      </LargeImage>
    </ImageSet>
  </ImageSets>
  <ItemAttributes>
    <Author>T. コルメン</Author>
    <Author>R. リベスト</Author>
    <Author>C. シュタイン</Author>
    <Author>C. ライザーソン</Author>
    <Binding>単行本</Binding>
    <Creator Role="原著">Thomas H. Cormen</Creator>
    <Creator Role="原著">Clifford Stein</Creator>
    <Creator Role="原著">Ronald L. Rivest</Creator>
    <Creator Role="原著">Charles E. Leiserson</Creator>
    <Creator Role="翻訳">浅野 哲夫</Creator>
    <Creator Role="翻訳">岩野 和生</Creator>
    <Creator Role="翻訳">梅尾 博司</Creator>
    <Creator Role="翻訳">山下 雅史</Creator>
    <Creator Role="翻訳">和田 幸一</Creator>
    <EAN>9784764903357</EAN>
    <EANList>
      <EANListElement>9784764903357</EANListElement>
    </EANList>
    <Edition>改訂2</Edition>
    <ISBN>4764903350</ISBN>
    <Label>近代科学社</Label>
    <ListPrice>
      <Amount>4148</Amount>
      <CurrencyCode>JPY</CurrencyCode>
      <FormattedPrice>￥ 4,148</FormattedPrice>
    </ListPrice>
    <Manufacturer>近代科学社</Manufacturer>
    <NumberOfPages>408</NumberOfPages>
    <PackageDimensions>
      <Height Units="hundredths-inches">87</Height>
      <Length Units="hundredths-inches">1000</Length>
      <Weight Units="hundredths-pounds">176</Weight>
      <Width Units="hundredths-inches">724</Width>
    </PackageDimensions>
    <ProductGroup>Book</ProductGroup>
    <ProductTypeName>ABIS_BOOK</ProductTypeName>
    <PublicationDate>2007-03</PublicationDate>
    <Publisher>近代科学社</Publisher>
    <Studio>近代科学社</Studio>
    <Title>アルゴリズムの設計と解析手法 (アルゴリズムイントロダクション)</Title>
  </ItemAttributes>
</Item>